pyariable/__init__.py
pyariable/py.typed
pyariable-0.9.0.dist-info/METADATA
pyariable-0.9.0.dist-info/WHEEL
pyariable-0.9.0.dist-info/RECORD
