Metadata-Version: 2.1
Name: pyariable
Version: 0.9.0
Summary: Placeholder variables to aid in testing.
Home-page: https://github.com/willemt/pyariable
License: BSD-3-Clause
Keywords: testing,development
Author: Willem Thiart
Author-email: himself@willemthiart.com
Requires-Python: >=3.9,<4.0
Classifier: Development Status :: 3 - Alpha
Classifier: Intended Audience :: Developers
Classifier: License :: OSI Approved :: BSD License
Classifier: Programming Language :: Python :: 3
Classifier: Programming Language :: Python :: 3.9
Classifier: Programming Language :: Python :: 3.10
Classifier: Programming Language :: Python :: 3.11
Classifier: Programming Language :: Python :: 3.12
Classifier: Programming Language :: Python :: 3.5
Classifier: Programming Language :: Python :: 3.6
Classifier: Programming Language :: Python :: 3.7
Classifier: Programming Language :: Python :: 3.8
Classifier: Topic :: System :: Logging
Project-URL: Repository, https://github.com/willemt/pyariable
